speckcn2/__init__.py
speckcn2/io.py
speckcn2/loss.py
speckcn2/mlmodels.py
speckcn2/mlops.py
speckcn2/normalizer.py
speckcn2/plots.py
speckcn2/postprocess.py
speckcn2/preprocess.py
speckcn2/scnn.py
speckcn2/transformations.py
speckcn2/utils.py
speckcn2-2.0.1.dist-info/LICENSE
speckcn2-2.0.1.dist-info/METADATA
speckcn2-2.0.1.dist-info/WHEEL
speckcn2-2.0.1.dist-info/top_level.txt
speckcn2-2.0.1.dist-info/RECORD
