Metadata-Version: 2.1
Name: speckcn2
Version: 2.0.1
Summary: Estimate Cn2 from Speckle patterns using machine learning
Author-email: Simone Ciarella <s.ciarella@esciencecenter.nl>
License: Apache 2.0 License
Project-URL: homepage, https://github.com/MALES-project/SpeckleCn2Profiler
Project-URL: issues, https://github.com/MALES-project/SpeckleCn2Profiler/issues
Project-URL: documentation, https://speckcn2.readthedocs.io
Project-URL: changelog, https://github.com/MALES-project/SpeckleCn2Profiler/releases
Keywords: python,machine learning,equivariant cnn,optical satelites,turbulence,laser communication
Classifier: Development Status :: 2 - Pre-Alpha
Classifier: Intended Audience :: Science/Research
Classifier: License :: OSI Approved :: Apache Software License
Classifier: Natural Language :: English
Classifier: Operating System :: OS Independent
Classifier: Programming Language :: Python :: 3
Classifier: Programming Language :: Python :: 3.10
Classifier: Programming Language :: Python :: 3.9
Classifier: Topic :: Scientific/Engineering
Requires-Python: >=3.9
License-File: LICENSE
Requires-Dist: matplotlib>=3.6.0
Requires-Dist: numpy
Requires-Dist: scipy>=1.9.3
Requires-Dist: torch
Requires-Dist: torchvision
Requires-Dist: PyYAML
Requires-Dist: cython
Requires-Dist: lie-learn-escience
Requires-Dist: escnn-escience
Requires-Dist: h5py
Provides-Extra: develop
Requires-Dist: bump-my-version; extra == "develop"
Requires-Dist: coverage[toml]; extra == "develop"
Requires-Dist: docformatter; extra == "develop"
Requires-Dist: mypy; extra == "develop"
Requires-Dist: pre-commit; extra == "develop"
Requires-Dist: pytest; extra == "develop"
Requires-Dist: pytest-mpl; extra == "develop"
Requires-Dist: pytest-dependency; extra == "develop"
Requires-Dist: pytest-image-diff; extra == "develop"
Provides-Extra: docs
Requires-Dist: markdown-include; extra == "docs"
Requires-Dist: mkdocs; extra == "docs"
Requires-Dist: mkdocs-jupyter; extra == "docs"
Requires-Dist: mkdocs-material; extra == "docs"
Requires-Dist: mkdocstrings[python]; extra == "docs"
Provides-Extra: publishing
Requires-Dist: twine; extra == "publishing"
Requires-Dist: wheel; extra == "publishing"
Requires-Dist: build; extra == "publishing"
Requires-Dist: tomllib; extra == "publishing"
